apic_tool/__init__.py
apic_tool/cli.py
apic_tool/extraction.py
apic_tool/insertion.py
apic_tool/workers/__init__.py
apic_tool/workers/baseworker.py
apic_tool/workers/mp3worker.py
id3autosort/__init__.py
id3autosort/cli.py
id3autosort/sorter.py
music_metadata_tools-2.0.0.dist-info/LICENSE
music_metadata_tools-2.0.0.dist-info/METADATA
music_metadata_tools-2.0.0.dist-info/WHEEL
music_metadata_tools-2.0.0.dist-info/entry_points.txt
music_metadata_tools-2.0.0.dist-info/top_level.txt
music_metadata_tools-2.0.0.dist-info/RECORD
