Metadata-Version: 2.1
Name: music-metadata-tools
Version: 2.0.0
Summary: A collection of tools for manipulating and interacting with music metadata.
Home-page: https://github.com/mischif/music-metadata-tools
Author: Jeremy Brown
Author-email: mischif@users.noreply.github.com
License: NPOSL-3.0
Keywords: ID3,APIC
Platform: UNKNOWN
Classifier: Development Status :: 5 - Production/Stable
Classifier: Operating System :: OS Independent
Classifier: License :: OSI Approved :: Open Software License 3.0 (OSL-3.0)
Classifier: Programming Language :: Python :: 3
Classifier: Programming Language :: Python :: 3.6
Classifier: Programming Language :: Python :: 3.7
Classifier: Programming Language :: Python :: 3.8
Requires-Python: ~=3.6
Requires-Dist: mutagen
Provides-Extra: test
Requires-Dist: codecov ; extra == 'test'
